aiextractor/__init__.py
aiextractor/extract.py
aiextractor/main.py
aiextractor-0.1.9.dist-info/WHEEL
aiextractor-0.1.9.dist-info/METADATA
aiextractor-0.1.9.dist-info/RECORD
