Metadata-Version: 2.1
Name: aiextractor
Version: 0.1.9
Summary: 
Author: mjaquier
Author-email: mjaquier@mjaquier.xyz
Requires-Python: >=3.8,<4.0
Classifier: Programming Language :: Python :: 3
Classifier: Programming Language :: Python :: 3.8
Requires-Dist: aihelper (>=0.2.8,<0.3.0)
Requires-Dist: pandas (>=1.1.2,<2.0.0)
Requires-Dist: pytest-cov (>=2.10.1,<3.0.0)
